tfcg/__init__.py
tfcg/graph_parser.py
tfcg/io.py
tfcg/networkx_helpler.py
tfcg/tf_attributes_parser.py
tfcg-0.1.4.dist-info/METADATA
tfcg-0.1.4.dist-info/WHEEL
tfcg-0.1.4.dist-info/top_level.txt
tfcg-0.1.4.dist-info/RECORD
