Metadata-Version: 2.1
Name: tfcg
Version: 0.1.4
Summary: tf_conceptual_graph
Home-page: https://github.com/0h-n0/tf_conceptual_graph
Author: Koji Ono
Author-email: kbu94982@gmail.com
License: UNKNOWN
Platform: UNKNOWN
Classifier: Programming Language :: Python :: 3.6
Requires-Python: >3.5
Requires-Dist: networkx
Requires-Dist: google
Provides-Extra: docs
Requires-Dist: sphinx (>=1.4) ; extra == 'docs'
Requires-Dist: sphinx-rtd-theme ; extra == 'docs'
